odoo9_addon_l10n_it_abicab-9.0.1.0.0.99.dev10-py2.7-nspkg.pth
odoo9_addon_l10n_it_abicab-9.0.1.0.0.99.dev10.dist-info/METADATA
odoo9_addon_l10n_it_abicab-9.0.1.0.0.99.dev10.dist-info/RECORD
odoo9_addon_l10n_it_abicab-9.0.1.0.0.99.dev10.dist-info/WHEEL
odoo9_addon_l10n_it_abicab-9.0.1.0.0.99.dev10.dist-info/namespace_packages.txt
odoo9_addon_l10n_it_abicab-9.0.1.0.0.99.dev10.dist-info/top_level.txt
odoo_addons/l10n_it_abicab/README.rst
odoo_addons/l10n_it_abicab/__init__.py
odoo_addons/l10n_it_abicab/__openerp__.py
odoo_addons/l10n_it_abicab/abicab.py
odoo_addons/l10n_it_abicab/abicab_view.xml
odoo_addons/l10n_it_abicab/i18n/ca.po
odoo_addons/l10n_it_abicab/i18n/de.po
odoo_addons/l10n_it_abicab/i18n/es.po
odoo_addons/l10n_it_abicab/i18n/fi.po
odoo_addons/l10n_it_abicab/i18n/fr.po
odoo_addons/l10n_it_abicab/i18n/it.po
odoo_addons/l10n_it_abicab/i18n/l10n_it_abicab.pot
odoo_addons/l10n_it_abicab/i18n/nb_NO.po
odoo_addons/l10n_it_abicab/i18n/sl.po
odoo_addons/l10n_it_abicab/static/description/icon.png
odoo_addons/l10n_it_abicab/test/abicab.yml
