Metadata-Version: 2.1
Name: odoo9-addon-l10n-it-abicab
Version: 9.0.1.0.0.99.dev10
Summary: Base Bank ABI/CAB codes
Home-page: http://www.odoo-italia.org/
Author: Odoo Italian Community, Odoo Community Association (OCA)
Author-email: support@odoo-community.org
License: AGPL-3
Platform: UNKNOWN
Classifier: Programming Language :: Python
Classifier: Framework :: Odoo
Classifier: License :: OSI Approved :: GNU Affero General Public License v3
Requires-Python: ~=2.7
Requires-Dist: odoo (<9.1a,>=9.0a)
